skill_local_music/LICENSE.md
skill_local_music/README.md
skill_local_music/__init__.py
skill_local_music/skill.json
skill_local_music/version.py
skill_local_music/locale/en-us/vocab/local.voc
skill_local_music/neon_skill_local_music.egg-info/PKG-INFO
skill_local_music/neon_skill_local_music.egg-info/SOURCES.txt
skill_local_music/neon_skill_local_music.egg-info/dependency_links.txt
skill_local_music/neon_skill_local_music.egg-info/entry_points.txt
skill_local_music/neon_skill_local_music.egg-info/requires.txt
skill_local_music/neon_skill_local_music.egg-info/top_level.txt
skill_local_music/test/test_skill.py
skill_local_music/ui/music-solid.svg
skill_local_music/util/__init__.py
neon_skill_local_music-3.2.0.dist-info/LICENSE.md
neon_skill_local_music-3.2.0.dist-info/METADATA
neon_skill_local_music-3.2.0.dist-info/WHEEL
neon_skill_local_music-3.2.0.dist-info/entry_points.txt
neon_skill_local_music-3.2.0.dist-info/top_level.txt
neon_skill_local_music-3.2.0.dist-info/RECORD
