Metadata-Version: 2.1
Name: neon-skill-local-music
Version: 3.2.0
Home-page: https://github.com/NeonGeckoCom/skill-local_music
Author: Neongecko
Author-email: developers@neon.ai
License: BSD-3-Clause
License-File: LICENSE.md
Requires-Dist: ovos-workshop>=0.0.7,~=0.0
Requires-Dist: ovos-plugin-common-play~=0.0
Requires-Dist: ovos-ocp-files-plugin~=0.13
Requires-Dist: ovos-utils>=0.0.28,~=0.0
Requires-Dist: ovos-skill-installer~=0.0.5
Requires-Dist: id3parse~=0.1
Provides-Extra: test
Requires-Dist: neon-minerva[padatious]~=0.3; extra == "test"
